pyxantech/__init__.py
pyxantech/config.py
pyxantech/protocol.py
pyxantech/protocols/acurus.yaml
pyxantech/protocols/dayton.yaml
pyxantech/protocols/monoprice.yaml
pyxantech/protocols/sonance.yaml
pyxantech/protocols/xantech.yaml
pyxantech/protocols/zpr68.yaml
pyxantech/series/dax88.yaml
pyxantech/series/monoprice6.yaml
pyxantech/series/sonance6.yaml
pyxantech/series/xantech8.yaml
pyxantech/series/zpr68-10.yaml
pyxantech-0.9.0.dist-info/licenses/LICENSE
pyxantech-0.9.0.dist-info/METADATA
pyxantech-0.9.0.dist-info/WHEEL
pyxantech-0.9.0.dist-info/top_level.txt
pyxantech-0.9.0.dist-info/zip-safe
pyxantech-0.9.0.dist-info/RECORD
