Metadata-Version: 2.4
Name: pyxantech
Version: 0.9.0
Home-page: https://github.com/rsnodgrass/pyxantech
Download-URL: https://github.com/rsnodgrass/pyxantech/archive/0.9.0.tar.gz
License: MIT
Classifier: Development Status :: 4 - Beta
Classifier: Programming Language :: Python :: 3.10
Classifier: Programming Language :: Python :: 3.11
Classifier: Programming Language :: Python :: 3.12
Classifier: Programming Language :: Python :: 3.13
Requires-Python: >=3.10
License-File: LICENSE
Requires-Dist: pyserial>=3.4
Requires-Dist: pyserial-asyncio>=0.4
Provides-Extra: tests
Requires-Dist: pytest; extra == "tests"
Dynamic: download-url
Dynamic: license-file
